<?xml version='1.0' encoding='utf-8'?>
<Texts Type="Other">
	<List>
		<Text Name="SuperPart_Rabbit_1">
			<Prefix>ดวงตา</Prefix>
			<Suffix>หยกโลหิต</Suffix>
			<Desc>Bí Thể huyết mạch của Thỏ Thượng Cổ. Tôi luyện mắt bằng Chân Hỏa, dùng nó kích thích Mộc khí trong gan làm nhiên liệu. Khi đạt đỉnh cao có thể cảm nhận mọi biến động của khí.</Desc>
			<Levels.0.Title>ชั้นที่หนึ่ง</Levels.0.Title>
			<Levels.0.Desc>เพิ่มความแม่นยำในการโจมตีของThể chấtเร้นลับเล็กน้อย\n เพิ่มโอกาสสำเร็จในการป้องกันของThể chấtเร้นลับเล็กน้อย</Levels.0.Desc>
			<Levels.1.Title>ชั้นที่สอง</Levels.1.Title>
			<Levels.1.Desc>เพิ่มโอกาสในการสะกดข่มอาวุธวิเศษของThể chấtเร้นลับเล็กน้อย\n เพิ่มโอกาสโจมตีทะลุเกราะปราณของผู้ฝึกตนวิถีThể chấtอมตะเล็กน้อย</Levels.1.Desc>
			<Levels.2.Title>ชั้นที่สาม</Levels.2.Title>
			<Levels.2.Desc>เพิ่มประสิทธิภาพการเดินลมปราณของผู้ฝึกตนวิถีThể chấtอมตะเล็กน้อย</Levels.2.Desc>
		</Text>
		<Text Name="SuperPart_Rabbit_2">
			<Prefix>เท้า</Prefix>
			<Suffix>เหยียบเมฆา</Suffix>
			<Desc>Bí Thể huyết mạch của Thỏ Thượng Cổ. Tôi luyện tai và chân bằng bí thuật, phối hợp chúng nhịp nhàng, mang lại tốc độ và giác quan siêu phàm.</Desc>
			<Levels.0.Title>ชั้นที่หนึ่ง</Levels.0.Title>
			<Levels.0.Desc>เพิ่มฐานการหลบหลีกของผู้ฝึกตนวิถีThể chấtอมตะเป็นอย่างมาก</Levels.0.Desc>
		</Text>
	</List>
</Texts>